pedantic/__init__.py
pedantic/constants.py
pedantic/env_var_logic.py
pedantic/exceptions.py
pedantic/get_context.py
pedantic/helper_methods.py
pedantic/decorators/__init__.py
pedantic/decorators/class_decorators.py
pedantic/decorators/cls_deco_frozen_dataclass.py
pedantic/decorators/fn_deco_context_manager.py
pedantic/decorators/fn_deco_count_calls.py
pedantic/decorators/fn_deco_deprecated.py
pedantic/decorators/fn_deco_does_same_as_function.py
pedantic/decorators/fn_deco_in_subprocess.py
pedantic/decorators/fn_deco_mock.py
pedantic/decorators/fn_deco_overrides.py
pedantic/decorators/fn_deco_pedantic.py
pedantic/decorators/fn_deco_rename_kwargs.py
pedantic/decorators/fn_deco_require_kwargs.py
pedantic/decorators/fn_deco_retry.py
pedantic/decorators/fn_deco_timer.py
pedantic/decorators/fn_deco_trace.py
pedantic/decorators/fn_deco_trace_if_returns.py
pedantic/decorators/fn_deco_unimplemented.py
pedantic/decorators/fn_deco_validate/__init__.py
pedantic/decorators/fn_deco_validate/convert_value.py
pedantic/decorators/fn_deco_validate/exceptions.py
pedantic/decorators/fn_deco_validate/fn_deco_validate.py
pedantic/decorators/fn_deco_validate/parameters/__init__.py
pedantic/decorators/fn_deco_validate/parameters/abstract_external_parameter.py
pedantic/decorators/fn_deco_validate/parameters/abstract_parameter.py
pedantic/decorators/fn_deco_validate/parameters/deserializable.py
pedantic/decorators/fn_deco_validate/parameters/environment_variable_parameter.py
pedantic/decorators/fn_deco_validate/parameters/flask_parameters.py
pedantic/decorators/fn_deco_validate/validators/__init__.py
pedantic/decorators/fn_deco_validate/validators/abstract_validator.py
pedantic/decorators/fn_deco_validate/validators/composite_validator.py
pedantic/decorators/fn_deco_validate/validators/datetime_isoformat.py
pedantic/decorators/fn_deco_validate/validators/datetime_unix_timestamp.py
pedantic/decorators/fn_deco_validate/validators/email.py
pedantic-2.3.2.dist-info/licenses/LICENSE
pedantic-2.3.2.dist-info/METADATA
pedantic-2.3.2.dist-info/WHEEL
pedantic-2.3.2.dist-info/top_level.txt
pedantic-2.3.2.dist-info/RECORD
