Metadata-Version: 2.4
Name: pedantic
Version: 2.3.2
Summary: Some useful Python decorators for cleaner software development.
Author-email: Willi Sontopski <willi_sontopski@arcor.de>
Maintainer-email: Willi Sontopski <willi_sontopski@arcor.de>
License-Expression: Apache-2.0
Project-URL: Bug Tracker, https://github.com/LostInDarkMath/pedantic-python-decorators/issues
Project-URL: Documentation, https://lostindarkmath.github.io/pedantic-python-decorators/pedantic/
Project-URL: Source Code, https://github.com/LostInDarkMath/pedantic-python-decorators
Keywords: decorators,tools,helpers,type-checking,pedantic,type annotations
Classifier: Programming Language :: Python :: 3
Classifier: Operating System :: OS Independent
Requires-Python: >=3.11
License-File: LICENSE
Provides-Extra: dev
Requires-Dist: docstring-parser==0.17; extra == "dev"
Requires-Dist: Flask[async]==3.1.2; extra == "dev"
Requires-Dist: multiprocess==0.70.18; extra == "dev"
Requires-Dist: Werkzeug==3.1.3; extra == "dev"
Dynamic: license-file
